deepnote_core/__init__.py
deepnote_core/config/__init__.py
deepnote_core/config/cli.py
deepnote_core/config/commands/__init__.py
deepnote_core/config/commands/describe.py
deepnote_core/config/commands/generate.py
deepnote_core/config/commands/get.py
deepnote_core/config/commands/migrate.py
deepnote_core/config/commands/paths.py
deepnote_core/config/commands/print.py
deepnote_core/config/commands/set.py
deepnote_core/config/commands/show.py
deepnote_core/config/commands/utils.py
deepnote_core/config/commands/validate.py
deepnote_core/config/installation_detector.py
deepnote_core/config/loader.py
deepnote_core/config/models.py
deepnote_core/config/persist.py
deepnote_core/config/resources.py
deepnote_core/config/xdg_paths.py
deepnote_core/execution/__init__.py
deepnote_core/execution/context.py
deepnote_core/execution/registry.py
deepnote_core/pydantic_compat_helpers.py
deepnote_core/resources/ipython/profile_default/ipython_config.py
deepnote_core/resources/ipython/profile_default/ipython_kernel_config.py
deepnote_core/resources/ipython/profile_default/startup/10-disable-jupyter-client-warnings.py
deepnote_core/resources/ipython/profile_default/startup/README
deepnote_core/resources/jupyter/jupyter_server_config.py
deepnote_core/resources/jupyter/kernel-startup.sh
deepnote_core/resources/scripts/get_integration_vars.py
deepnote_core/resources/scripts/github_credential_helper.py
deepnote_core/resources/scripts/prometheus_metrics.py
deepnote_core/runtime/__init__.py
deepnote_core/runtime/plan.py
deepnote_core/runtime/types.py
deepnote_toolkit/__init__.py
deepnote_toolkit/__main__.py
deepnote_toolkit/_version.py
deepnote_toolkit/chart/__init__.py
deepnote_toolkit/chart/deepnote_chart.py
deepnote_toolkit/chart/spec_utils.py
deepnote_toolkit/chart/types.py
deepnote_toolkit/chart/utils.py
deepnote_toolkit/cli/__init__.py
deepnote_toolkit/cli/main.py
deepnote_toolkit/cli/server.py
deepnote_toolkit/config.py
deepnote_toolkit/create_ssh_tunnel.py
deepnote_toolkit-1.2.1.dist-info/METADATA
deepnote_toolkit-1.2.1.dist-info/WHEEL
deepnote_toolkit-1.2.1.dist-info/entry_points.txt
deepnote_toolkit-1.2.1.dist-info/licenses/LICENSE
deepnote_toolkit-1.2.1.dist-info/RECORD
